aiotuyalan/__init__.py
aiotuyalan/device.py
aiotuyalan/light.py
aiotuyalan/lib/__init__.py
aiotuyalan/lib/client.py
aiotuyalan-0.0.3.dist-info/LICENSE
aiotuyalan-0.0.3.dist-info/METADATA
aiotuyalan-0.0.3.dist-info/WHEEL
aiotuyalan-0.0.3.dist-info/top_level.txt
aiotuyalan-0.0.3.dist-info/RECORD
