Metadata-Version: 2.1
Name: aiotuyalan
Version: 0.0.3
Summary: Python library for interacting with Tuya-based devices using asyncio
Home-page: https://github.com/zachcheatham/async-tuya
Author: Zach Cheatham
Author-email: zachcheatham@gmail.com
License: UNKNOWN
Platform: UNKNOWN
Classifier: Programming Language :: Python :: 3
Classifier: License :: OSI Approved :: MIT License
Classifier: Operating System :: OS Independent
Requires-Python: >=3.5.3
Requires-Dist: pyaes (>=1.6.1)
